qualkit/anchored_topic_model.py
qualkit/clean.py
qualkit/keywords.py
qualkit/sentiment.py
qualkit/stopwords.py
qualkit/topics.py
qualkit-0.1.5.dist-info/LICENSE
qualkit-0.1.5.dist-info/METADATA
qualkit-0.1.5.dist-info/WHEEL
qualkit-0.1.5.dist-info/top_level.txt
qualkit-0.1.5.dist-info/RECORD
