Metadata-Version: 2.1
Name: qualkit
Version: 0.1.5
Summary: Python qualitative analysis toolkit with utilities and simplified wrappers for common algorithms
Home-page: https://github.com/JiscDACT/qualkit
Download-URL: https://github.com/JiscDACT/qualkit/tarball/0.1.5
Author: Scott Wilson
Author-email: scott.wilson@jisc.ac.uk
License: BSD
Classifier: Development Status :: 4 - Beta
Classifier: License :: OSI Approved :: BSD License
Classifier: Topic :: Scientific/Engineering :: Mathematics
Classifier: Topic :: Software Development :: Libraries :: Python Modules
Classifier: Programming Language :: Python :: 3.6
Classifier: Programming Language :: Python :: 3.7
License-File: LICENSE
Requires-Dist: pandas (>=1.1.5)
Requires-Dist: numpy (>=1.19.5)
Requires-Dist: nltk (>=3.6.2)
Requires-Dist: scikit-learn (>=0.24.2)
Requires-Dist: corextopic (>=1.1)
